fgutils/__init__.py
fgutils/const.py
fgutils/fgconfig.py
fgutils/its.py
fgutils/parse.py
fgutils/permutation.py
fgutils/proxy.py
fgutils/query.py
fgutils/rdkit.py
fgutils/utils.py
fgutils/algorithm/__init__.py
fgutils/algorithm/subgraph.py
fgutils/algorithm/subgraph_enumeration.py
fgutils/chem/__init__.py
fgutils/chem/ps.py
fgutils/chem/valence.py
fgutils/data/RawTUDataset.py
fgutils/data/__init__.py
fgutils/data/loader.py
fgutils/proxy_collection/__init__.py
fgutils/proxy_collection/common.py
fgutils/proxy_collection/diels_alder_proxy.py
fgutils/synthesis/__init__.py
fgutils/synthesis/rule_application.py
fgutils/torch/ITSDataset.py
fgutils/torch/TUDataset.py
fgutils/torch/__init__.py
fgutils/torch/graph.py
fgutils/torch/utils.py
fgutils/vis/__init__.py
fgutils/vis/common.py
fgutils/vis/proxy.py
fgutils/vis/svg.py
fgutils-0.2.32.dist-info/METADATA
fgutils-0.2.32.dist-info/WHEEL
fgutils-0.2.32.dist-info/licenses/LICENSE
fgutils-0.2.32.dist-info/RECORD
