Metadata-Version: 2.4
Name: fgutils
Version: 0.2.32
Summary: Library to get functional groups from molecular graphs.
Project-URL: homepage, https://github.com/klausweinbauer/FGUtils
Project-URL: source, https://github.com/klausweinbauer/FGUtils
Project-URL: issues, https://github.com/klausweinbauer/FGUtils/issues
Author-email: Klaus Weinbauer <klaus@bioinf.uni-leipzig.de>
License-File: LICENSE
Classifier: License :: OSI Approved :: MIT License
Classifier: Operating System :: OS Independent
Classifier: Programming Language :: Python :: 3
Requires-Python: >=3.11
Requires-Dist: networkx>=3.2
Requires-Dist: numpy>=1.26.3
Requires-Dist: rdkit>=2023.9.4
